{
  "type_of_material": "News", 
  "blog": [], 
  "news_desk": "None", 
  "lead_paragraph": "Kuwait is not a \"free-rider\" in U.S.-led campaigns against terrorism and other threats, a senior Kuwaiti security official said on Thursday, rejecting comments by President Barack Obama critical of some U.S. allies.", 
  "headline": {
    "main": "Kuwait Security Chief to Obama: We're Not Free-Riders", 
    "print_headline": "Kuwait Security Chief to Obama: We're Not Free-Riders"
  }, 
  "abstract": null, 
  "print_page": null, 
  "word_count": "686", 
  "_id": "56eada4438f0d82753b971d1", 
  "snippet": "Kuwait is not a \"free-rider\" in U.S.-led campaigns against terrorism and other threats, a senior Kuwaiti security official said on Thursday, rejecting comments by President Barack Obama critical of some U.S. allies.", 
  "source": "Reuters", 
  "slideshow_credits": null, 
  "web_url": "http://www.nytimes.com/reuters/2016/03/17/world/middleeast/17reuters-gulf-security-usa.html", 
  "multimedia": [], 
  "subsection_name": "Middle East", 
  "keywords": [], 
  "byline": {
    "person": [], 
    "original": "By REUTERS", 
    "organization": "REUTERS"
  }, 
  "document_type": "article", 
  "pub_date": "2016-03-17T12:22:18Z", 
  "section_name": "World"
}