{
  "type_of_material": "News", 
  "blog": [], 
  "news_desk": "None", 
  "lead_paragraph": "England coach Eddie Jones says he wants fiery captain Dylan Hartley to play like Tarzan when the Six Nations tournament kicks off against Scotland at Murrayfield on Saturday.", 
  "headline": {
    "main": "Jones Wants England Captain Hartley to 'Play Like Tarzan'", 
    "print_headline": "Jones Wants England Captain Hartley to 'Play Like Tarzan'"
  }, 
  "abstract": null, 
  "print_page": null, 
  "word_count": "334", 
  "_id": "56afbb807988105fa9a9c2ab", 
  "snippet": "England coach Eddie Jones says he wants fiery captain Dylan Hartley to play like Tarzan when the Six Nations tournament kicks off against Scotland at Murrayfield on Saturday.", 
  "source": "Reuters", 
  "slideshow_credits": null, 
  "web_url": "http://www.nytimes.com/reuters/2016/02/01/sports/rugby/01reuters-rugby-union-england-hartley.html", 
  "multimedia": [], 
  "subsection_name": "Rugby", 
  "keywords": [], 
  "byline": {
    "person": [], 
    "original": "By REUTERS", 
    "organization": "REUTERS"
  }, 
  "document_type": "article", 
  "pub_date": "2016-02-01T15:06:24Z", 
  "section_name": "Sports"
}